{
  "items": [
    {
      "term": "protome",
      "kind": "word",
      "cefrLevel": null,
      "senses": [
        {
          "pos": "noun",
          "definition": "A protome is the head and upper body part of a figure, often used as a decorative motif on artifacts or architecture.",
          "examples": [
            "In ancient art, a protome could be carved at the top of a vessel.",
            "The bronze protome depicted a lion's head against a dark background."
          ],
          "collocations": ["protome decoration", "stone protome", "animal protome", "frontal protome", "head protome"],
          "synonyms": ["protoma", "protomask"],
          "antonyms": [],
          "register": "formal",
          "domain": ["art", "history", "archaeology"]
        }
      ]
    },
    {
      "term": "protomeristem",
      "kind": "word",
      "cefrLevel": null,
      "senses": [
        {
          "pos": "noun",
          "definition": "A promeristem is a region in plants consisting of actively dividing cells that will form the plant’s tissues, located at the growing tip.",
          "examples": [
            "The promeristem gives rise to new leaves as the plant grows.",
            "Researchers study promeristem activity to understand how shoots form."
          ],
          "collocations": ["apical promeristem", "meristematic cells", "primordia in promeristem"],
          "synonyms": ["primordium region", "initial meristem"],
          "antonyms": [],
          "register": "formal",
          "domain": ["biology", "botany", "academic"]
        }
      ]
    },
    {
      "term": "protomerite",
      "kind": "word",
      "cefrLevel": null,
      "senses": [
        {
          "pos": "noun",
          "definition": "Protomerite is a term used in biology to refer to an early, undifferentiated segment or segmental unit in certain organisms during development.",
          "examples": [
            "During the larval stage, the protomerite contributes to body segmentation.",
            "Cells in the protomerite later specialize to form distinct tissues."
          ],
          "collocations": ["protomerite region", "protomerite cells"],
          "synonyms": [],
          "antonyms": [],
          "register": "formal",
          "domain": ["biology", "developmental biology", "academic"]
        }
      ]
    },
    {
      "term": "protomeritic",
      "kind": "word",
      "cefrLevel": null,
      "senses": [
        {
          "pos": "adjective",
          "definition": "Protomeritic describes something related to or characteristic of a protomerite or the early developmental segment in organisms.",
          "examples": [
            "Protomeritic tissue shows early signs of differentiation.",
            "The protomeritic region is crucial for initial body plan formation."
          ],
          "collocations": ["protomeritic tissue", "protomeritic development"],
          "synonyms": [],
          "antonyms": [],
          "register": "formal",
          "domain": ["biology", "anatomy", "academic"]
        }
      ]
    },
    {
      "term": "protometal",
      "kind": "word",
      "cefrLevel": null,
      "senses": [
        {
          "pos": "noun",
          "definition": "Protometal refers to a precursor form of metal or to pre-metallic material or music described as a precursor to heavy metal.",
          "examples": [
            "The archeologist found protometal artifacts showing early metalworking.",
            "In music, protometal describes early heavy metal sounds."
          ],
          "collocations": ["proto metal", "protometal era", "protometal music"],
          "synonyms": ["precursor metal", "early metal"],
          "antonyms": [],
          "register": "neutral",
          "domain": ["science", "music", "history"]
        }
      ]
    },
    {
      "term": "protometallic",
      "kind": "word",
      "cefrLevel": null,
      "senses": [
        {
          "pos": "adjective",
          "definition": "Protometallic describes something relating to a precursor form of metal or to early metal music traits.",
          "examples": [
            "The protometallic style influenced later rock genres.",
            "Researchers studied protometallic alloys in ancient artifacts."
          ],
          "collocations": ["protometallic alloy", "protometallic sound"],
          "synonyms": [],
          "antonyms": [],
          "register": "neutral",
          "domain": ["science", "music", "history"]
        }
      ]
    },
    {
      "term": "protometals",
      "kind": "word",
      "cefrLevel": null,
      "senses": [
        {
          "pos": "noun",
          "definition": "Protometals is the plural form referring to early or precursor metals or to early metal music styles collectively.",
          "examples": [
            "Museum displays protometals alongside early smelted artifacts.",
            "The genre traces its roots to protometals combined with blues ideas."
          ],
          "collocations": ["protometals collection", "protometals era"],
          "synonyms": [],
          "antonyms": [],
          "register": "neutral",
          "domain": ["history", "music", "archaeology"]
        }
      ]
    },
    {
      "term": "protometaphrast",
      "kind": "word",
      "cefrLevel": null,
      "senses": [
        {
          "pos": "noun",
          "definition": "Protometaphrast is a rare term likely referring to an early writer or author in a proto-literary tradition.",
          "examples": [
            "The manuscript hints at protometaphrast influences in ancient storytelling."
          ],
          "collocations": ["protometaphrast text", "proto-literary figure"],
          "synonyms": [],
          "antonyms": [],
          "register": "formal",
          "domain": ["literature", "history", "academic"]
        }
      ]
    },
    {
      "term": "protominobacter",
      "kind": "word",
      "cefrLevel": null,
      "senses": [
        {
          "pos": "noun",
          "definition": "Protominobacter refers to a primitive or early form of bacterium in biological classification.",
          "examples": [
            "Protominobacter species are studied to understand early bacterial evolution."
          ],
          "collocations": ["protominobacter strain", "proto-bacteria"],
          "synonyms": [],
          "antonyms": [],
          "register": "formal",
          "domain": ["biology", "microbiology", "academic"]
        }
      ]
    },
    {
      "term": "protomonadina",
      "kind": "word",
      "cefrLevel": null,
      "senses": [
        {
          "pos": "noun",
          "definition": "Protomonadina is a plural or collective term used in biology, referring to early stem or monad-like organisms or structures.",
          "examples": [
            "Fossils show protomonadina-like formations indicating ancient life stages."
          ],
          "collocations": ["protomonadina structures"],
          "synonyms": [],
          "antonyms": [],
          "register": "formal",
          "domain": ["biology", "paleontology", "academic"]
        }
      ]
    },
    {
      "term": "protomonostelic",
      "kind": "word",
      "cefrLevel": null,
      "senses": [
        {
          "pos": "noun",
          "definition": "Protomonostelic refers to an early form of the vascular stele (central axis) in plant anatomy.",
          "examples": [
            "The protomonostelic arrangement shows primitive vascular tissue organization."
          ],
          "collocations": ["protomonostelic cylinder", "monostelic precursor"],
          "synonyms": [],
          "antonyms": [],
          "register": "formal",
          "domain": ["botany", "anatomy", "academic"]
        }
      ]
    },
    {
      "term": "protomorph",
      "kind": "word",
      "cefrLevel": null,
      "senses": [
        {
          "pos": "noun",
          "definition": "Protomorph is an early or primitive form of a morph, referring to initial shape or form in biology or geology.",
          "examples": [
            "The fossil reveals a protomorph of the species."
          ],
          "collocations": ["protomorph form", "protomorphotype"],
          "synonyms": [],
          "antonyms": [],
          "register": "formal",
          "domain": ["biology", "paleontology", "science"]
        }
      ]
    },
    {
      "term": "protomorphic",
      "kind": "word",
      "cefrLevel": null,
      "senses": [
        {
          "pos": "adjective",
          "definition": "Protomorphic describes something that has the form or characteristics of a protomorph; in early development or evolution.",
          "examples": [
            "The specimen shows protomorphic traits."
          ],
          "collocations": ["protomorphic features"],
          "synonyms": [],
          "antonyms": [],
          "register": "formal",
          "domain": ["biology", "paleontology", "academic"]
        }
      ]
    },
    {
      "term": "protomycetales",
      "kind": "word",
      "cefrLevel": null,
      "senses": [
        {
          "pos": "noun",
          "definition": "Protomycetales is an order in the biological classification of fungi, representing early fungal lineages.",
          "examples": [
            "Protomycetales includes several ancient fungal species."
          ],
          "collocations": ["protomycetales fungi"],
          "synonyms": [],
          "antonyms": [],
          "register": "formal",
          "domain": ["biology", "mycology", "academic"]
        }
      ]
    },
    {
      "term": "protomyosinose",
      "kind": "word",
      "cefrLevel": null,
      "senses": [
        {
          "pos": "noun",
          "definition": "Protomyosinose is a rare medical term referring to a condition involving early or proto-like myosin activity or muscle tissue development.",
          "examples": [
            "Clinical notes mention protomyosinose in relation to muscle formation disorders."
          ],
          "collocations": ["protomyosinose condition"],
          "synonyms": [],
          "antonyms": [],
          "register": "medical",
          "domain": ["medicine", "anatomy", "clinical"]
        }
      ]
    },
    {
      "term": "proton",
      "kind": "word",
      "cefrLevel": null,
      "senses": [
        {
          "pos": "noun",
          "definition": "A proton is a positively charged particle in the nucleus of an atom.",
          "examples": [
            "A proton has a positive charge."
          ],
          "collocations": ["positive charge", "nucleus", "hydrogen atom"],
          "synonyms": ["positron (not exact; close concept)"],
          "antonyms": ["electron"],
          "register": "neutral",
          "domain": ["science", "physics", "education"]
        }
      ]
    },
    {
      "term": "protonate",
      "kind": "word",
      "cefrLevel": null,
      "senses": [
        {
          "pos": "verb",
          "definition": "To protonate means to add a proton (a positively charged hydrogen nucleus) to a molecule or ion.",
          "examples": [
            "Acidic solutions protonate the compound.",
            "The base will protonate the amine group."
          ],
          "collocations": ["protonate a molecule", "protonate ion", "protonation reaction"],
          "synonyms": ["add a proton", "hydrogenate (context-dependent)"],
          "antonyms": [],
          "register": "formal",
          "domain": ["chemistry", "chemistry education", "science"]
        }
      ]
    },
    {
      "term": "protonated",
      "kind": "word",
      "cefrLevel": null,
      "senses": [
        {
          "pos": "adjective",
          "definition": "Protonated describes a molecule that has received an additional proton.",
          "examples": [
            "The molecule became protonated under acidic conditions.",
            "Protonated species have different reactivity than their neutral forms."
          ],
          "collocations": ["protonated form", "protonated molecule"],
          "synonyms": [],
          "antonyms": [],
          "register": "formal",
          "domain": ["chemistry", "science"]
        }
      ]
    },
    {
      "term": "protonates",
      "kind": "word",
      "cefrLevel": null,
      "senses": [
        {
          "pos": "verb",
          "definition": "To protonate means to add a proton to a molecule or ion (third-person singular present).",
          "examples": [
            "The acid protonates the amine group.",
            "It protonates the compound rapidly in solution."
          ],
          "collocations": ["protonates the molecule", "acid protonates"],
          "synonyms": ["adds a proton"],
          "antonyms": [],
          "register": "formal",
          "domain": ["chemistry", "science"]
        }
      ]
    },
    {
      "term": "protonating",
      "kind": "word",
      "cefrLevel": null,
      "senses": [
        {
          "pos": "verb",
          "definition": "Protonating is the process of adding a proton to a molecule or ion.",
          "examples": [
            "Protonating the molecule changes its charge.",
            "The solution shows rapid protonating under acid conditions."
          ],
          "collocations": ["protonating agent", "protonating step"],
          "synonyms": [],
          "antonyms": [],
          "register": "formal",
          "domain": ["chemistry", "science"]
        }
      ]
    },
    {
      "term": "protonation",
      "kind": "word",
      "cefrLevel": null,
      "senses": [
        {
          "pos": "noun",
          "definition": "Protonation is the act or process of adding a proton to a molecule or ion.",
          "examples": [
            "Protonation states influence reaction mechanisms.",
            "The pH affects the rate of protonation."
          ],
          "collocations": ["rate of protonation", "protonation step"],
          "synonyms": [],
          "antonyms": [],
          "register": "formal",
          "domain": ["chemistry", "biochemistry", "science"]
        }
      ]
    },
    {
      "term": "protonations",
      "kind": "word",
      "cefrLevel": null,
      "senses": [
        {
          "pos": "noun",
          "definition": "Protonations are instances or quantities of protonation in chemical reactions.",
          "examples": [
            "Multiple protonations can occur in polybasic molecules.",
            "The study compares different protonations in solution."
          ],
          "collocations": ["multiple protonations", "protonations events"],
          "synonyms": [],
          "antonyms": [],
          "register": "formal",
          "domain": ["chemistry", "science"]
        }
      ]
    },
    {
      "term": "protone",
      "kind": "word",
      "cefrLevel": null,
      "senses": [
        {
          "pos": "noun",
          "definition": "Protone is a historical or less common term for a primitive or early proton-like particle in some theoretical contexts.",
          "examples": [
            "Some older theories used protone to refer to a primitive charge carrier."
          ],
          "collocations": ["protone particle"],
          "synonyms": [],
          "antonyms": [],
          "register": "archaic",
          "domain": ["physics", "history of science"]
        }
      ]
    },
    {
      "term": "protonegroid",
      "kind": "word",
      "cefrLevel": null,
      "senses": [
        {
          "pos": "noun",
          "definition": "Protonegroid refers to an early or primitive form of a hypothetical anthropoid or negroid group in historical anthropological contexts.",
          "examples": [
            "Protonegroid concepts are outdated and discouraged in modern anthropology."
          ],
          "collocations": ["protonegroid type"],
          "synonyms": [],
          "antonyms": [],
          "register": "archaic",
          "domain": ["anthropology", "history", "ethnography"]
        }
      ]
    },
    {
      "term": "protonema",
      "kind": "word",
      "cefrLevel": null,
      "senses": [
        {
          "pos": "noun",
          "definition": "Protonema is the thread-like early stage of a moss gametophyte that grows from a spore.",
          "examples": [
            "The protonema spreads over the moist surface before forming leaves.",
            "Researchers study protonema to understand moss development."
          ],
          "collocations": ["protonema filaments", "protonema stage"],
          "synonyms": [],
          "antonyms": [],
          "register": "neutral",
          "domain": ["botany", "mycology", "biology"]
        }
      ]
    }
  ]
}