{
  "items": [
    {
      "term": "qabala",
      "kind": "word",
      "cefrLevel": "null",
      "senses": [
        {
          "pos": "noun",
          "definition": "a variant spelling of qabalāh or qabalah, referring to a system of Jewish mysticism involving esoteric interpretation of the Hebrew Bible",
          "examples": ["She studied qabala to understand hidden meanings in the Torah."],
          "collocations": ["kabbalah", "modern qabala", "occult qabala", "study of qabala"],
          "synonyms": ["qabalah", "cabala", "kabbalah"],
          "antonyms": [],
          "register": "formal",
          "domain": ["religion", "academic", "general"]
        }
      ]
    },
    {
      "term": "qabalah",
      "kind": "word",
      "cefrLevel": "null",
      "senses": [
        {
          "pos": "noun",
          "definition": "the esoteric doctrine of the Kabbalah; Jewish mysticism interpreted in various traditions",
          "examples": ["The scholar compared qabalah to other mystical traditions."],
          "collocations": ["Kabbalah", "study of qabalah", "qabalistic traditions"],
          "synonyms": ["kabbalah", "cabala", "qabalah"],
          "antonyms": [],
          "register": "formal",
          "domain": ["religion", "academic"]
        }
      ]
    },
    {
      "term": "qabalahs",
      "kind": "word",
      "cefrLevel": "null",
      "senses": [
        {
          "pos": "noun",
          "definition": "plural form of qabalah; multiple instances or branches of the esoteric doctrine",
          "examples": ["Various qabalahs offer different interpretations."],
          "collocations": ["different qabalahs", "study of qabalahs"],
          "synonyms": ["qabalas", "kabbalahs"],
          "antonyms": [],
          "register": "formal",
          "domain": ["religion", "academic"]
        }
      ]
    },
    {
      "term": "qabalas",
      "kind": "word",
      "cefrLevel": "null",
      "senses": [
        {
          "pos": "noun",
          "definition": "alternate plural form of qabalah; the esoteric traditions of Kabbalah",
          "examples": ["Learned about different qabalas across cultures."],
          "collocations": ["various qabalas", "qabalistic schools"],
          "synonyms": ["qabalahs", "kabbalahs"],
          "antonyms": [],
          "register": "formal",
          "domain": ["religion", "academic"]
        }
      ]
    },
    {
      "term": "qabalism",
      "kind": "word",
      "cefrLevel": "null",
      "senses": [
        {
          "pos": "noun",
          "definition": "the practice or study of qabalah; the mystical interpretation tradition",
          "examples": ["He followed an early form of qabalism."],
          "collocations": [" qabala studies", "quabalistic qabalism"],
          "synonyms": ["kabbalah study", "cabala practice"],
          "antonyms": [],
          "register": "formal",
          "domain": ["religion", "academia"]
        }
      ]
    },
    {
      "term": "qabalisms",
      "kind": "word",
      "cefrLevel": "null",
      "senses": [
        {
          "pos": "noun",
          "definition": "plural of qabalism; different systems or schools within qabalah",
          "examples": ["There are several qabalisms within Hermetic traditions."],
          "collocations": ["different qabalisms", "hermetic qabalisms"],
          "synonyms": ["qabalism", "kabbalistic schools"],
          "antonyms": [],
          "register": "formal",
          "domain": ["religion", "occult"]
        }
      ]
    },
    {
      "term": "qabalist",
      "kind": "word",
      "cefrLevel": "null",
      "senses": [
        {
          "pos": "noun",
          "definition": "a person who studies or practices qabalah",
          "examples": ["The qabalist explained the tree of life."],
          "collocations": ["qabalist traditions", "renowned qabalist"],
          "synonyms": ["kabbalist", "cabala practitioner"],
          "antonyms": [],
          "register": "formal",
          "domain": ["religion", "academic"]
        }
      ]
    },
    {
      "term": "qabalistic",
      "kind": "word",
      "cefrLevel": "null",
      "senses": [
        {
          "pos": "adjective",
          "definition": "relating to qabalah or its interpretation",
          "examples": ["A qabalistic interpretation requires symbolic reasoning."],
          "collocations": ["qabalistic teaching", "qabalistic symbolism"],
          "synonyms": ["kabbalistic", "cabbalistic"],
          "antonyms": [],
          "register": "formal",
          "domain": ["religion", "academic"]
        }
      ]
    },
    {
      "term": "qabalists",
      "kind": "word",
      "cefrLevel": "null",
      "senses": [
        {
          "pos": "noun",
          "definition": "plural of qabalist; multiple practitioners or scholars of qabalah",
          "examples": ["Several qabalists contributed to the manuscript."],
          "collocations": ["qabalists of the era", "well-known qabalists"],
          "synonyms": ["kabbalists", "cabala practitioners"],
          "antonyms": [],
          "register": "formal",
          "domain": ["religion", "academic"]
        }
      ]
    },
    {
      "term": "qabbala",
      "kind": "word",
      "cefrLevel": "null",
      "senses": [
        {
          "pos": "noun",
          "definition": "alternate spelling of qabalah; the mystical tradition of Kabbalah",
          "examples": ["He studied qabbala in depth."],
          "collocations": ["qabbala study", "qabbala tradition"],
          "synonyms": ["qabalah", "kabbalah"],
          "antonyms": [],
          "register": "formal",
          "domain": ["religion", "academic"]
        }
      ]
    },
    {
      "term": "qabbalah",
      "kind": "word",
      "cefrLevel": "null",
      "senses": [
        {
          "pos": "noun",
          "definition": "a Jewish mystical interpretation of the scriptures; sometimes used more broadly for related esoteric systems",
          "examples": ["The book explores qabbalah and its symbols."],
          "collocations": ["forest of symbols in qabbalah", "qabbalah study"],
          "synonyms": ["qabalah", "qabalism", "kabalah"],
          "antonyms": [],
          "register": "formal",
          "domain": ["religion", "academic"]
        }
      ]
    },
    {
      "term": "qadarite",
      "kind": "word",
      "cefrLevel": "null",
      "senses": [
        {
          "pos": "noun",
          "definition": "historical or religious reference; a follower of qadar or fate-related beliefs in some Islamic traditions",
          "examples": ["The qadarite emphasized divine decree."],
          "collocations": ["qadarite beliefs", "qadarite sect"],
          "synonyms": ["predestinarian", "fatist"],
          "antonyms": [],
          "register": "formal",
          "domain": ["religion", "history"]
        }
      ]
    },
    {
      "term": "qadi",
      "kind": "word",
      "cefrLevel": "null",
      "senses": [
        {
          "pos": "noun",
          "definition": "a civil or religious judge in Islamic law",
          "examples": ["The qadi settled the dispute according to Sharia."],
          "collocations": ["qadi's court", "senior qadi", "qadi in the region"],
          "synonyms": ["judge", "mufti (contextual)"],
          "antonyms": [],
          "register": "formal",
          "domain": ["law", "religion", "government"]
        }
      ]
    },
    {
      "term": "qadis",
      "kind": "word",
      "cefrLevel": "null",
      "senses": [
        {
          "pos": "noun",
          "definition": "plural of qadi; multiple Islamic judges",
          "examples": ["Several qadis presided over the appeals."],
          "collocations": ["qadis in succession", "panel of qadis"],
          "synonyms": ["judges (in context)", "qadi"]
        ,
          "antonyms": [],
          "register": "formal",
          "domain": ["law", "religion", "government"]
        }
      ]
    },
    {
      "term": "qaimaqam",
      "kind": "word",
      "cefrLevel": "null",
      "senses": [
        {
          "pos": "noun",
          "definition": "a ceremonial or administrative title meaning a governor or local chief in some Muslim regions",
          "examples": ["The qaimaqam reviewed the district matters."],
          "collocations": ["qaimaqam office", "district qaimaqam"],
          "synonyms": ["governor", "chief", "magistrate"],
          "antonyms": [],
          "register": "formal",
          "domain": ["government", "politics"]
        }
      ]
    },
    {
      "term": "qaimaqams",
      "kind": "word",
      "cefrLevel": "null",
      "senses": [
        {
          "pos": "noun",
          "definition": "plural of qaimaqam; several local chiefs or governors",
          "examples": ["Several qaimaqams attended the ceremony."],
          "collocations": ["qaimaqams council", "regional qaimaqams"],
          "synonyms": ["governors", "chiefs"],
          "antonyms": [],
          "register": "formal",
          "domain": ["government", "politics"]
        }
      ]
    },
    {
      "term": "qajaq",
      "kind": "word",
      "cefrLevel": "null",
      "senses": [
        {
          "pos": "noun",
          "definition": "an Inuit single-person boat, also spelled kayak",
          "examples": ["She paddled the qajaq across the bay."],
          "collocations": ["qajaq paddling", "open-water qajaq"],
          "synonyms": ["kayak"],
          "antonyms": [],
          "register": "neutral",
          "domain": ["geography", "outdoors"]
        }
      ]
    },
    {
      "term": "qajaqs",
      "kind": "word",
      "cefrLevel": "null",
      "senses": [
        {
          "pos": "noun",
          "definition": "plural of qajaq; multiple kayaks",
          "examples": ["Several qajaqs lined the shore."],
          "collocations": ["qajaqs on the beach", "two qajaqs"],
          "synonyms": ["kayaks"],
          "antonyms": [],
          "register": "neutral",
          "domain": ["geography", "outdoors"]
        }
      ]
    },
    {
      "term": "qalamdan",
      "kind": "word",
      "cefrLevel": "null",
      "senses": [
        {
          "pos": "noun",
          "definition": "an inkwell or pen case, used in traditional calligraphy",
          "examples": ["The qalamdan held a fine nib."],
          "collocations": ["ornate qalamdan", "qalamdan for writing"],
          "synonyms": ["ink case", "pen case"],
          "antonyms": [],
          "register": "formal",
          "domain": ["art", "culture"]
        }
      ]
    },
    {
      "term": "qalamdans",
      "kind": "word",
      "cefrLevel": "null",
      "senses": [
        {
          "pos": "noun",
          "definition": "plural of qalamdan; multiple pen cases",
          "examples": ["The museum displayed several qalamdans."],
          "collocations": ["qalamdans collection", "ornate qalamdans"],
          "synonyms": ["ink cases"],
          "antonyms": [],
          "register": "formal",
          "domain": ["art", "culture"]
        }
      ]
    },
    {
      "term": "qamutik",
      "kind": "word",
      "cefrLevel": "null",
      "senses": [
        {
          "pos": "noun",
          "definition": "a traditional sled used by Inuit peoples, often pulled by dogs",
          "examples": ["They rode a qamutik across the snow."],
          "collocations": ["dog-drawn qamutik", "sled qamutik"],
          "synonyms": ["sled", "dog-sled"],
          "antonyms": [],
          "register": "neutral",
          "domain": ["culture", "geography"]
        }
      ]
    },
    {
      "term": "qamutiks",
      "kind": "word",
      "cefrLevel": "null",
      "senses": [
        {
          "pos": "noun",
          "definition": "plural of qamutik; multiple sleds",
          "examples": ["Two qamutiks followed the caravan."],
          "collocations": ["qamutiks fleet", "qamutiks on the ice"],
          "synonyms": ["sleds"],
          "antonyms": [],
          "register": "neutral",
          "domain": ["culture", "geography"]
        }
      ]
    }
  ]
}