{
  "items": [
    {
      "term": "snubbinesses",
      "kind": "word",
      "cefrLevel": "null",
      "senses": [
        {
          "pos": "noun",
          "definition": "plural of snubbiness: the quality of being snub; discourteous or contemptuous behavior or manner",
          "examples": [
            "Her snubbinesses toward colleagues made the meeting tense.",
            "They noticed his snubbinesses when he dismissed their ideas."
          ],
          "collocations": ["snubbinesses in behavior", "air of snubbinesses", "display of snubbinesses"],
          "synonyms": ["contemptuousness", "disdain", "rudeness"],
          "antonyms": ["courtesy", "politeness", "warmth"],
          "register": "informal",
          "domain": ["general", "everyday"]
        }
      ]
    },
    {
      "term": "snubbing",
      "kind": "gerund",
      "cefrLevel": "B2",
      "senses": [
        {
          "pos": "verb",
          "definition": "the act of treating someone with disdain or ignoring them on purpose",
          "examples": [
            "She felt snubbing when no one invited her to the party.",
            "Snubbing him in public can damage a relationship."
          ],
          "collocations": ["snubbing someone", "social snubbing", "snubbed by peers"],
          "synonyms": ["contemptuous treatment", "disregard", "rebuff"],
          "antonyms": ["acceptance", "inclusion", "warm reception"],
          "register": "informal",
          "domain": ["general", "social"]
        }
      ]
    },
    {
      "term": "snubbingly",
      "kind": "adverb",
      "cefrLevel": "null",
      "senses": [
        {
          "pos": "adverb",
          "definition": "in a way that snubs someone; in a contemptuous or dismissive manner",
          "examples": [
            "She spoke snubbingly to the assistant.",
            "He waved him away snubbingly."
          ],
          "collocations": ["snubbingly dismissive", "snubbingly coldly"],
          "synonyms": ["contemptuously", "disparagingly", "disdainfully"],
          "antonyms": [],
          "register": "informal",
          "domain": ["general"]
        }
      ]
    },
    {
      "term": "snubbings",
      "kind": "word",
      "cefrLevel": "null",
      "senses": [
        {
          "pos": "noun",
          "definition": "plural of snubbing; instances of ignoring or dismissing someone",
          "examples": [
            "Several snubbings at the event made him withdraw.",
            "Her snubbings during negotiations left the team frustrated."
          ],
          "collocations": ["snubbings in social settings", "public snubbings"],
          "synonyms": ["rebuffs", "disparagements", "dismissals"],
          "antonyms": [],
          "register": "informal",
          "domain": ["general", "social"]
        }
      ]
    },
    {
      "term": "snubbish",
      "kind": "word",
      "cefrLevel": "B1",
      "senses": [
        {
          "pos": "adjective",
          "definition": "showing disdainful or snobbish behavior; contemptuously dismissive",
          "examples": [
            "Her snubbish attitude put everyone off.",
            "A snubbish remark can hurt feelings."
          ],
          "collocations": ["snubbish remark", "snubbish attitude", "snubbish behavior"],
          "synonyms": ["contemptuous", "snooty", "snobbish"],
          "antonyms": ["friendly", "polite", "humble"],
          "register": "informal",
          "domain": ["general"]
        }
      ]
    },
    {
      "term": "snubbishly",
      "kind": "adverb",
      "cefrLevel": "null",
      "senses": [
        {
          "pos": "adverb",
          "definition": "in a snobbish or contemptuous manner",
          "examples": [
            "He spoke snubbishly to the waiter.",
            "They snubbishly refused to acknowledge the guide."
          ],
          "collocations": ["snubbishly dismissively", "snubbishly arrogant"],
          "synonyms": ["contemptuously", "snobbishly"],
          "antonyms": [],
          "register": "informal",
          "domain": ["general"]
        }
      ]
    },
    {
      "term": "snubbishness",
      "kind": "word",
      "cefrLevel": "null",
      "senses": [
        {
          "pos": "noun",
          "definition": "the quality of being snubbish; snobbish or disdainful behavior",
          "examples": [
            "Her snubbishness alienated colleagues.",
            "The snubbishness of the reply surprised everyone."
          ],
          "collocations": ["visible snubbishness", "air of snubbishness"],
          "synonyms": ["snobbishness", "disdain", "rudeness"],
          "antonyms": ["kindness", "courtesy", "politeness"],
          "register": "informal",
          "domain": ["general"]
        }
      ]
    },
    {
      "term": "snubby",
      "kind": "word",
      "cefrLevel": "A2",
      "senses": [
        {
          "pos": "adjective",
          "definition": "having a short, blunt nose; also used informally to describe something blunt or stocky",
          "examples": [
            "A snubby nose is characteristic of some breeds.",
            "A snubby pencil sits oddly in the cup."
          ],
          "collocations": ["snubby nose", "snubby shape", "snubby car"],
          "synonyms": ["stubby", "short-nosed"],
          "antonyms": ["long-nosed", "pointed"],
          "register": "informal",
          "domain": ["general"]
        }
      ]
    },
    {
      "term": "snubfin",
      "kind": "phrase",
      "cefrLevel": "null",
      "senses": [
        {
          "pos": "noun",
          "definition": "a type of dolphin with a short, blunt dorsal fin, indigenous name: snubfin dolphin",
          "examples": [
            "We saw a snubfin dolphin offshore.",
            "Conservationists study the snubfin dolphin habitat."
          ],
          "collocations": ["snubfin dolphin", "snubfin whale? (note: common confusion)"],
          "synonyms": ["snubfin dolphin"],
          "antonyms": [],
          "register": "neutral",
          "domain": ["environment", "science"]
        }
      ]
    },
    {
      "term": "snubness",
      "kind": "word",
      "cefrLevel": "null",
      "senses": [
        {
          "pos": "noun",
          "definition": "the state or quality of being snub; a snub",
          "examples": [
            "His snubness was obvious when he ignored the invitation.",
            "She could not hide her snubness at the party."
          ],
          "collocations": ["social snub", "felt snubness"],
          "synonyms": ["rebuff", "snub", "disdain"],
          "antonyms": [],
          "register": "informal",
          "domain": ["general", "social"]
        }
      ]
    },
    {
      "term": "snubnesses",
      "kind": "word",
      "cefrLevel": "null",
      "senses": [
        {
          "pos": "noun",
          "definition": "plural of snubness; multiple instances of snubs or rebuffs",
          "examples": [
            "The snubnesses from peers were numerous that week.",
            "Her snubnesses added to his sense of isolation."
          ],
          "collocations": ["series of snubnesses", "snubnesses in social settings"],
          "synonyms": ["rebuffs", "rebukes"],
          "antonyms": [],
          "register": "informal",
          "domain": ["general", "social"]
        }
      ]
    },
    {
      "term": "snubnose",
      "kind": "phrase",
      "cefrLevel": "B1",
      "senses": [
        {
          "pos": "noun",
          "definition": "a short, blunt nose or a type of dog with a short nose",
          "examples": [
            "The snubnose bulldog has a flat face.",
            "A snubnose may require careful breathing care."
          ],
          "collocations": ["snubnose dog", "flat-faced snubnose"],
          "synonyms": ["snub-nose", "flat-nosed"],
          "antonyms": [],
          "register": "informal",
          "domain": ["general", "pets"]
        }
      ]
    },
    {
      "term": "snubproof",
      "kind": "word",
      "cefrLevel": "null",
      "senses": [
        {
          "pos": "adjective",
          "definition": "describing something that cannot be snubbed or easily rebuffed; resistant to snubs",
          "examples": [
            "The snubproof branding survived the critique.",
            "They sought snubproof etiquette in negotiations."
          ],
          "collocations": ["snubproof defense", "snubproof strategy"],
          "synonyms": ["unrebuffable", "unassailable"],
          "antonyms": [],
          "register": "formal",
          "domain": ["business", "general"]
        }
      ]
    },
    {
      "term": "snubs",
      "kind": "word",
      "cefrLevel": "null",
      "senses": [
        {
          "pos": "noun",
          "definition": "plural of snub; acts of rebuffing or ignoring someone",
          "examples": [
            "Their many snubs made him hesitate.",
            "She endured several snubs at the event."
          ],
          "collocations": ["social snubs", "slights and snubs"],
          "synonyms": ["rebuffs", "rebukes", "slights"],
          "antonyms": [],
          "register": "informal",
          "domain": ["general", "social"]
        },
        {
          "pos": "verb",
          "definition": "third person singular of snub: to rebuff or ignore someone",
          "examples": [
            "She snubs him at every meeting.",
            "The editor snubs new submissions from outsiders."
          ],
          "collocations": ["snubs reporters", "snubs proposals"],
          "synonyms": ["rebuffs", "rebukes"],
          "antonyms": [],
          "register": "informal",
          "domain": ["general", "media"]
        }
      ]
    },
    {
      "term": "snuck",
      "kind": "verb",
      "cefrLevel": "A2",
      "senses": [
        {
          "pos": "verb",
          "definition": "past tense of sneak: moved quietly or secretly",
          "examples": [
            "She snuck out of the room while they argued.",
            "The cat snuck behind the couch."
          ],
          "collocations": ["snuck past", "snuck away"],
          "synonyms": ["slid", "crept", "stealthed"],
          "antonyms": ["entered openly", "walked in"],
          "register": "informal",
          "domain": ["general"]
        }
      ]
    },
    {
      "term": "snudge",
      "kind": "word",
      "cefrLevel": "null",
      "senses": [
        {
          "pos": "verb",
          "definition": "to push something in a sluggish, dragging manner; to scratch or rub softly",
          "examples": [
            "He snudged the door open with his shoulder.",
            "The dog snudged its nose along the carpet."
          ],
          "collocations": ["snudging a chair", "snudging along"],
          "synonyms": ["drag", "nudge", "push slowly"],
          "antonyms": [],
          "register": "informal",
          "domain": ["general"]
        }
      ]
    },
    {
      "term": "snudged",
      "kind": "verb",
      "cefrLevel": "null",
      "senses": [
        {
          "pos": "verb",
          "definition": "past tense of snudge",
          "examples": [
            "She snudged the box back into place.",
            "He snudged the blanket over his legs."
          ],
          "collocations": ["snudged the box", "snudged along"],
          "synonyms": ["nudged", "dragged"],
          "antonyms": [],
          "register": "informal",
          "domain": ["general"]
        }
      ]
    },
    {
      "term": "snudgery",
      "kind": "word",
      "cefrLevel": "null",
      "senses": [
        {
          "pos": "noun",
          "definition": "work or activity that is dull or dreary; drudgery",
          "examples": [
            "The snudgery of paperwork wore him down.",
            "She quit because of the constant snudgery at the office."
          ],
          "collocations": ["daily snudgery", "snudgery tasks"],
          "synonyms": ["drudgery", "tedium"],
          "antonyms": [],
          "register": "neutral",
          "domain": ["work", "general"]
        }
      ]
    },
    {
      "term": "snudges",
      "kind": "word",
      "cefrLevel": "null",
      "senses": [
        {
          "pos": "verb",
          "definition": "third person singular of snudge: pushes or rubs something slowly",
          "examples": [
            "He snudges the door open with his shoulder.",
            "The boat snudges through the shallow water."
          ],
          "collocations": ["snudges aside", "snudges forward"],
          "synonyms": ["nudges", "pushes slowly"],
          "antonyms": [],
          "register": "informal",
          "domain": ["general"]
        }
      ]
    },
    {
      "term": "snudging",
      "kind": "verb",
      "cefrLevel": "null",
      "senses": [
        {
          "pos": "verb",
          "definition": "gerund of snudge: pushing or rubbing slowly",
          "examples": [
            "Snudging the cart along the curb was tough.",
            "They were snudging through the crowd."
          ],
          "collocations": ["snudging along", "snudging forward"],
          "synonyms": ["nudging", "pushing slowly"],
          "antonyms": [],
          "register": "informal",
          "domain": ["general"]
        }
      ]
    },
    {
      "term": "snuff",
      "kind": "word",
      "cefrLevel": "A2",
      "senses": [
        {
          "pos": "verb",
          "definition": "to extinguish a flame or to stop a candle from burning",
          "examples": [
            "Please snuff the candle before you leave.",
            "The candle was snuffed out by a gust of wind."
          ],
          "collocations": ["snuff out", "snuffed candle"],
          "synonyms": ["extinguish", "put out"],
          "antonyms": ["light", "ignite"],
          "register": "neutral",
          "domain": ["general", "household"]
        },
        {
          "pos": "noun",
          "definition": "powdered tobacco pressed into a small plug; also the sense of the material used to scent or flavor",
          "examples": [
            "He dipped a pinch of snuff between his fingers.",
            "Snuff tobacco has a strong scent."
          ],
          "collocations": ["tobacco snuff", "snuff box"],
          "synonyms": ["tobacco", "powdered tobacco"],
          "antonyms": [],
          "register": "informal",
          "domain": ["substance", "lifestyle"]
        }
      ]
    },
    {
      "term": "snuffbox",
      "kind": "word",
      "cefrLevel": "A2",
      "senses": [
        {
          "pos": "noun",
          "definition": "a small, ornate box used to hold snuff",
          "examples": [
            "The antique snuffbox belonged to his great-grandfather.",
            "She opened the snuffbox and sniffed the powder."
          ],
          "collocations": ["snuffbox collection", "gold snuffbox"],
          "synonyms": ["snuff container"],
          "antonyms": [],
          "register": "neutral",
          "domain": ["history", "lifestyle"]
        }
      ]
    },
    {
      "term": "snuffboxer",
      "kind": "word",
      "cefrLevel": "null",
      "senses": [
        {
          "pos": "noun",
          "definition": "a person who uses or makes snuffboxes; a traditional term for a snuffer or worker around snuffboxes",
          "examples": [
            "Collectors prized the snuffboxer’s craftsmanship.",
            "A famous snuffboxer carved delicate designs."
          ],
          "collocations": ["snuffboxer craftsman"],
          "synonyms": [],
          "antonyms": [],
          "register": "archaic",
          "domain": ["history", "art"]
        }
      ]
    },
    {
      "term": "snuffboxes",
      "kind": "word",
      "cefrLevel": "null",
      "senses": [
        {
          "pos": "noun",
          "definition": "plural of snuffbox",
          "examples": [
            "The museum displayed several antique snuffboxes.",
            "Her collection included ornate snuffboxes."
          ],
          "collocations": ["antique snuffboxes", "snuffbox collection"],
          "synonyms": ["snuffboxes"],
          "antonyms": [],
          "register": "neutral",
          "domain": ["history", "collecting"]
        }
      ]
    },
    {
      "term": "snuffcolored",
      "kind": "word",
      "cefrLevel": "null",
      "senses": [
        {
          "pos": "adjective",
          "definition": "having a dark brown color like snuff; brownish-black shade",
          "examples": [
            "The snuffcolored fur blended with the shadows.",
            "They wore snuffcolored jackets for the event."
          ],
          "collocations": ["snuffcolored fur", "snuffcolored clothing"],
          "synonyms": ["dark brown", "brownish-black"],
          "antonyms": [],
          "register": "literary",
          "domain": ["general", "fashion"]
        }
      ]
    }
  ]
}