{
  "items": [
    {
      "term": "careers",
      "kind": "word",
      "cefrLevel": "B2",
      "senses": [
        {
          "pos": "noun",
          "definition": "the professional life or work that a person does, especially in a chosen field or occupation",
          "examples": [
            "She has had a successful career in teaching.",
            "Many people change careers in their 30s.",
            "Career development requires planning and effort."
          ],
          "collocations": ["career path", "career goals", "career advancement", "career prospects", "career woman/man"],
          "synonyms": ["profession", "occupation", "vocation"],
          "antonyms": ["unemployment", "retirement"],
          "register": "formal",
          "domain": ["general", "employment", "education"]
        }
      ]
    },
    {
      "term": "carefox",
      "kind": "word",
      "cefrLevel": null,
      "senses": [
        {
          "pos": "noun",
          "definition": "no common meaning in contemporary English; may be a coined brand or proper noun",
          "examples": [
            "The brand CareFox offers health tracking services." 
          ],
          "collocations": ["brand", "product", "brand name"],
          "synonyms": [],
          "antonyms": [],
          "register": "null",
          "domain": ["business", "technology"]
        }
      ]
    },
    {
      "term": "carefree",
      "kind": "word",
      "cefrLevel": "A2",
      "senses": [
        {
          "pos": "adjective",
          "definition": "free from worry or anxiety; not bothered by problems",
          "examples": [
            "They spent a carefree summer at the beach.",
            "Her carefree attitude helped her stay positive."
          ],
          "collocations": ["carefree attitude", "carefree lifestyle", "carefree days"],
          "synonyms": ["lighthearted", "untroubled", "easygoing"],
          "antonyms": ["worried", "anxious", "tense"],
          "register": "informal",
          "domain": ["general", "emotional"]
        }
      ]
    },
    {
      "term": "carefreenesses",
      "kind": "word",
      "cefrLevel": null,
      "senses": [
        {
          "pos": "noun",
          "definition": "plural form; the state or quality of being carefree",
          "examples": [
            "Her carefreenesses were contagious and everyone relaxed."
          ],
          "collocations": ["carefreeness", "mood of carefreeness"],
          "synonyms": [],
          "antonyms": [],
          "register": "neutral",
          "domain": ["general"]
        }
      ]
    },
    {
      "term": "carefreenesses",
      "kind": "word",
      "cefrLevel": null,
      "senses": [
        {
          "pos": "noun",
          "definition": "plural form; the states or qualities of being carefree",
          "examples": [
            "The conference highlighted various carefreenesses of youth."
          ],
          "collocations": ["levels of carefreeness"],
          "synonyms": [],
          "antonyms": [],
          "register": "neutral",
          "domain": ["general"]
        }
      ]
    },
    {
      "term": "careful",
      "kind": "word",
      "cefrLevel": "B2",
      "senses": [
        {
          "pos": "adjective",
          "definition": "giving careful attention to avoid mistakes or danger; cautious",
          "examples": [
            "Be careful crossing the street.",
            "She is very careful with her money.",
            "A careful assessment was made before proceeding."
          ],
          "collocations": ["careful about", "careful consideration", "careful planning", "careful approach"],
          "synonyms": ["cautious", "prudent", "attentive"],
          "antonyms": ["careless", "rash"],
          "register": "neutral",
          "domain": ["general", "education", "business"]
        }
      ]
    },
    {
      "term": "carefull",
      "kind": "word",
      "cefrLevel": null,
      "senses": [
        {
          "pos": "noun",
          "definition": "nonstandard/incorrect spelling of 'careful'; not a separate sense in modern English",
          "examples": [
            "Note: 'carefull' is usually a misspelling of 'careful'."
          ],
          "collocations": ["misspelling"],
          "synonyms": [],
          "antonyms": [],
          "register": "informal",
          "domain": ["general"]
        }
      ]
    },
    {
      "term": "carefuller",
      "kind": "word",
      "cefrLevel": null,
      "senses": [
        {
          "pos": "adjective",
          "definition": "nonstandard comparative form; likely intended as 'carefuler' or more commonly 'more careful' (not standard in English)",
          "examples": [
            "This usage is rare and often considered incorrect."
          ],
          "collocations": ["more careful", "carefully more"],
          "synonyms": [],
          "antonyms": [],
          "register": "informal",
          "domain": ["general"]
        }
      ]
    },
    {
      "term": "carefullest",
      "kind": "word",
      "cefrLevel": null,
      "senses": [
        {
          "pos": "adjective",
          "definition": "nonstandard superlative form; intended as 'most careful' but not standard",
          "examples": [
            "He is the carefullest driver I know."
          ],
          "collocations": ["most careful"],
          "synonyms": [],
          "antonyms": [],
          "register": "informal",
          "domain": ["general"]
        }
      ]
    },
    {
      "term": "carefully",
      "kind": "word",
      "cefrLevel": "A2",
      "senses": [
        {
          "pos": "adverb",
          "definition": "with care and attention; in a careful way",
          "examples": [
            "She carefully organized the files.",
            "Look carefully before you jump.",
            "He spoke carefully to avoid offense."
          ],
          "collocations": ["carefully planned", "carefully consider", "carefully done"],
          "synonyms": ["meticulously", "thoroughly", "cautiously"],
          "antonyms": ["carelessly", "hastily"],
          "register": "neutral",
          "domain": ["general", "education"]
        }
      ]
    },
    {
      "term": "carefulness",
      "kind": "word",
      "cefrLevel": "B1",
      "senses": [
        {
          "pos": "noun",
          "definition": "the quality of being careful to avoid mistakes or danger",
          "examples": [
            "Her carefulness helped prevent accidents.",
            "We approached the task with great carefulness."
          ],
          "collocations": ["great carefulness", "with carefulness", "displayed carefulness"],
          "synonyms": ["carefulness", "prudence", " vigilance"],
          "antonyms": ["carelessness"],
          "register": "neutral",
          "domain": ["general", "safety"]
        }
      ]
    },
    {
      "term": "carefulnesses",
      "kind": "word",
      "cefrLevel": null,
      "senses": [
        {
          "pos": "noun",
          "definition": "plural form; multiple instances or displays of carefulness",
          "examples": [
            "The safety briefing highlighted several carefulnesses."
          ],
          "collocations": ["different carefulnesses"],
          "synonyms": [],
          "antonyms": [],
          "register": "neutral",
          "domain": ["general"]
        }
      ]
    },
    {
      "term": "caregiver",
      "kind": "word",
      "cefrLevel": "A2",
      "senses": [
        {
          "pos": "noun",
          "definition": "a person who provides care for someone else, such as a child, sick person, or elderly person",
          "examples": [
            "The caregiver looked after the elderly neighbor.",
            "Many caregivers work long hours."
          ],
          "collocations": ["caregiver role", "professional caregiver", "family caregiver"],
          "synonyms": ["carer", "helper", "care assistant"],
          "antonyms": [],
          "register": "neutral",
          "domain": ["healthcare", "general"]
        }
      ]
    },
    {
      "term": "caregivers",
      "kind": "word",
      "cefrLevel": "A2",
      "senses": [
        {
          "pos": "noun",
          "definition": "plural of caregiver",
          "examples": [
            "Many caregivers juggle work and family responsibilities."
          ],
          "collocations": ["family caregivers", "professional caregivers"],
          "synonyms": ["carers"],
          "antonyms": [],
          "register": "neutral",
          "domain": ["healthcare", "general"]
        }
      ]
    },
    {
      "term": "caregiving",
      "kind": "word",
      "cefrLevel": "B1",
      "senses": [
        {
          "pos": "noun",
          "definition": "the act of providing care, especially for someone who is ill or dependent",
          "examples": [
            "She is balancing work with caregiving at home.",
            "Caregiving can be demanding but rewarding."
          ],
          "collocations": ["caregiving responsibilities", "formal caregiving", "paid caregiving"],
          "synonyms": ["taking care", "nursing", "assisting"],
          "antonyms": [],
          "register": "neutral",
          "domain": ["healthcare", "general"]
        }
      ]
    },
    {
      "term": "caregivings",
      "kind": "word",
      "cefrLevel": null,
      "senses": [
        {
          "pos": "noun",
          "definition": "plural of caregiving; instances of providing care",
          "examples": [
            "Family members shared several caregivings during the week."
          ],
          "collocations": ["caregiving sessions"],
          "synonyms": [],
          "antonyms": [],
          "register": "neutral",
          "domain": ["healthcare", "general"]
        }
      ]
    },
    {
      "term": "careless",
      "kind": "word",
      "cefrLevel": "A2",
      "senses": [
        {
          "pos": "adjective",
          "definition": "not taking care; not paying attention; reckless",
          "examples": [
            "He made a careless mistake on the report.",
            "Be careful not to be careless with your things.",
            "A careless driver caused the accident."
          ],
          "collocations": ["careless mistake", "careless with", "careless attitude"],
          "synonyms": ["reckless", "negligent", "sloppy"],
          "antonyms": ["careful", "meticulous"],
          "register": "neutral",
          "domain": ["general", "safety"]
        }
      ]
    },
    {
      "term": "carelessly",
      "kind": "word",
      "cefrLevel": "A2",
      "senses": [
        {
          "pos": "adverb",
          "definition": "in a careless way; without giving enough attention",
          "examples": [
            "He threw the papers carelessly onto the desk.",
            "Carelessly he forgot to save his work."
          ],
          "collocations": ["carelessly said", "carelessly thrown"],
          "synonyms": ["recklessly", "negligently"],
          "antonyms": ["carefully"],
          "register": "neutral",
          "domain": ["general"]
        }
      ]
    },
    {
      "term": "carelessness",
      "kind": "word",
      "cefrLevel": "A2",
      "senses": [
        {
          "pos": "noun",
          "definition": "the quality of not being careful; a lack of attention or caution",
          "examples": [
            "Carelessness led to multiple errors.",
            "Reduce carelessness by double-checking your work."
          ],
          "collocations": ["level of carelessness", "carelessness factors"],
          "synonyms": ["negligence", "inattention"],
          "antonyms": ["carefulness"],
          "register": "neutral",
          "domain": ["general", "education"]
        }
      ]
    },
    {
      "term": "carelessnesses",
      "kind": "word",
      "cefrLevel": null,
      "senses": [
        {
          "pos": "noun",
          "definition": "plural form; instances of carelessness",
          "examples": [
            "The report noted several carelessnesses that needed correction."
          ],
          "collocations": ["various carelessnesses"],
          "synonyms": [],
          "antonyms": [],
          "register": "neutral",
          "domain": ["general"]
        }
      ]
    },
    {
      "term": "careline",
      "kind": "word",
      "cefrLevel": null,
      "senses": [
        {
          "pos": "noun",
          "definition": "a hotline or telephone service for emotional support or health information; may also refer to a line of care products in branding",
          "examples": [
            "Call the careline for counseling support."
          ],
          "collocations": ["helpline", "support careline"],
          "synonyms": ["helpline", "help line"],
          "antonyms": [],
          "register": "neutral",
          "domain": ["healthcare", "general"]
        }
      ]
    },
    {
      "term": "carelines",
      "kind": "word",
      "cefrLevel": null,
      "senses": [
        {
          "pos": "noun",
          "definition": "plural of careline; multiple helplines or branding lines",
          "examples": [
            "The company operates several carelines for different services."
          ],
          "collocations": ["carelines across regions"],
          "synonyms": [],
          "antonyms": [],
          "register": "neutral",
          "domain": ["healthcare", "business"]
        }
      ]
    },
    {
      "term": "careme",
      "kind": "word",
      "cefrLevel": null,
      "senses": [
        {
          "pos": "noun",
          "definition": "likely a proper noun or archaic/placeholder; no common modern sense",
          "examples": [
            "Careme is a surname used in some historical texts."
          ],
          "collocations": ["Careme family", "Mr. Careme"],
          "synonyms": [],
          "antonyms": [],
          "register": "neutral",
          "domain": ["history", "general"]
        }
      ]
    },
    {
      "term": "caremes",
      "kind": "word",
      "cefrLevel": null,
      "senses": [
        {
          "pos": "noun",
          "definition": "plural of Careme (likely a proper noun); no general modern sense",
          "examples": [
            "The Caremes attended the event."
          ],
          "collocations": ["Caremes family"],
          "synonyms": [],
          "antonyms": [],
          "register": "neutral",
          "domain": ["history", "general"]
        }
      ]
    },
    {
      "term": "carene",
      "kind": "word",
      "cefrLevel": null,
      "senses": [
        {
          "pos": "noun",
          "definition": "uncommon or archaic term; may refer to a brand name or misspelling",
          "examples": [
            "Carene is not widely used in modern English."
          ],
          "collocations": ["carene brand"],
          "synonyms": [],
          "antonyms": [],
          "register": "archaic",
          "domain": ["general"]
        }
      ]
    }
  ]
}